longdllm/__init__.py
longdllm/configuration_llada.py
longdllm/core.py
longdllm/core_simplified.py
longdllm/diffucoder_patches.py
longdllm/generation.py
longdllm/llada_patches.py
longdllm/rope_classes.py
longdllm/utils.py
longdllm/data/diffucoder_rescale_factors.csv
longdllm/data/example_rescale_factors.txt
longdllm/data/llada_rescale_factors.csv
longdllm-0.1.5.dist-info/licenses/LICENSE
longdllm-0.1.5.dist-info/METADATA
longdllm-0.1.5.dist-info/WHEEL
longdllm-0.1.5.dist-info/top_level.txt
longdllm-0.1.5.dist-info/RECORD
