Metadata-Version: 2.4
Name: longdllm
Version: 0.1.5
Summary: Plug-and-play long context adaptation for diffusion language models
Home-page: https://github.com/lbertge/longdllm
Author: Albert Ge
Author-email: Albert Ge <lbertge@gmail.com>
Maintainer-email: Albert Ge <lbertge@gmail.com>
License: MIT
Project-URL: Homepage, https://github.com/lbertge/longdllm
Project-URL: Bug Reports, https://github.com/lbertge/longdllm/issues
Project-URL: Source, https://github.com/lbertge/longdllm
Project-URL: Documentation, https://github.com/lbertge/longdllm#readme
Keywords: transformer,long-context,rope,diffusion,language-model,llm
Classifier: Development Status :: 3 - Alpha
Classifier: Intended Audience :: Developers
Classifier: Intended Audience :: Science/Research
Classifier: License :: OSI Approved :: MIT License
Classifier: Operating System :: OS Independent
Classifier: Programming Language :: Python :: 3
Classifier: Programming Language :: Python :: 3.8
Classifier: Programming Language :: Python :: 3.9
Classifier: Programming Language :: Python :: 3.10
Classifier: Programming Language :: Python :: 3.11
Classifier: Topic :: Scientific/Engineering :: Artificial Intelligence
Classifier: Topic :: Software Development :: Libraries :: Python Modules
Requires-Python: >=3.8
License-File: LICENSE
Requires-Dist: torch<3.0.0,>=2.7.1
Requires-Dist: transformers<5.0.0,>=4.46.2
Requires-Dist: datasets<3.0.0,>=2.18.0
Requires-Dist: azureml-sdk
Requires-Dist: accelerate
Requires-Dist: numpy
Requires-Dist: pandas
Requires-Dist: einops
Requires-Dist: tqdm
Requires-Dist: mlflow
Requires-Dist: tiktoken
Requires-Dist: hf_transfer
Provides-Extra: dev
Requires-Dist: pytest>=6.0; extra == "dev"
Requires-Dist: pytest-cov>=2.0; extra == "dev"
Requires-Dist: black>=22.0; extra == "dev"
Requires-Dist: isort>=5.0; extra == "dev"
Requires-Dist: flake8>=4.0; extra == "dev"
Requires-Dist: mypy>=0.950; extra == "dev"
Provides-Extra: test
Requires-Dist: pytest>=6.0; extra == "test"
Requires-Dist: pytest-cov>=2.0; extra == "test"
Dynamic: author
Dynamic: home-page
Dynamic: license-file
Dynamic: requires-python
